{"importBase":"import","nativeBase":"native","name":"resources","deps":[],"uuids":["89Uo0rnotDR6NRIbyNKDpb","92/M07sbZESYeECnV6fwpY","11eb5cbc7","1bc8fd3b7","2eIplJljlJq6IlxWrXyhJ9","43L5HNGHhNc4E15lYmkbl5","60slupOLVLM6fQCi2epUQE","89Uo0rnotDR6NRIbyNKDpb@6c48a","89Uo0rnotDR6NRIbyNKDpb@f9941","8eyonOBuBGhLXmuDnGIQlc","92/M07sbZESYeECnV6fwpY@6c48a","92/M07sbZESYeECnV6fwpY@f9941","c7Jg6VGixNRb3WAltcg/rK","c9gxurCjRCEId7RsegROOS","e4aEG3rE1C+at0f86a7pIO","0e4f65650","11eb5cbc7@6c48a","1bc8fd3b7@6c48a","22ULmDZopFmooXXvQvceYF@f9941","2eIplJljlJq6IlxWrXyhJ9@6c48a","2eIplJljlJq6IlxWrXyhJ9@f9941","4aske/ZdFGWrrV5vlUqg0E@f9941","60slupOLVLM6fQCi2epUQE@6c48a","60slupOLVLM6fQCi2epUQE@f9941","a62xlWvRlAU7/ULrPAADjd","b7XeMshKZC2YBZmLl8rY05@f9941","b9ld6xAPhKuI6FOj+lK6JM@f9941","c4DX4XQlJGy5HcM1AyjY3c@f9941","c9gxurCjRCEId7RsegROOS@6c48a","feMgKxH3xGJox5/70FVacs@f9941"],"paths":{"0":["textures/rewardIcons/1001",1,1],"1":["textures/rewardIcons/1000",1,1],"5":["prefabs/view/AlertBoxView",0,1],"7":["textures/rewardIcons/1001/texture",2,1],"8":["textures/rewardIcons/1001/spriteFrame",3,1],"9":["prefabs/view/BannerTipView",0,1],"10":["textures/rewardIcons/1000/texture",2,1],"11":["textures/rewardIcons/1000/spriteFrame",3,1],"12":["prefabs/view/LoadingView",0,1],"14":["prefabs/view/LoadingTipView",0,1]},"scenes":{},"packs":{"0e4f65650":[2,16,3,17,18,4,19,20,5,21,6,22,23,0,7,8,9,1,10,11,24,25,26,27,12,13,28,14,29]},"versions":{"import":[15,"75723"],"native":[2,"c1213",3,"58871",4,"fc642",6,"41f9b",0,"abef8",1,"a852d",13,"0b5cf"]},"redirect":[],"debug":false,"extensionMap":{},"hasPreloadScript":true,"dependencyRelationships":{},"types":["cc.Prefab","cc.ImageAsset","cc.Texture2D","cc.SpriteFrame"]}